energy_assistant/__init__.py
energy_assistant/alembic.ini
energy_assistant/constants.py
energy_assistant/db.py
energy_assistant/main.py
energy_assistant/mqtt.py
energy_assistant/optimizer_base.py
energy_assistant/py.typed
energy_assistant/settings.py
energy_assistant/websocket.py
energy_assistant/api/__init__.py
energy_assistant/api/base.py
energy_assistant/api/main.py
energy_assistant/api/config/__init__.py
energy_assistant/api/config/schema.py
energy_assistant/api/config/use_cases.py
energy_assistant/api/config/views.py
energy_assistant/api/device/__init__.py
energy_assistant/api/device/schema.py
energy_assistant/api/device/use_cases.py
energy_assistant/api/device/views.py
energy_assistant/api/forecast/__init__.py
energy_assistant/api/forecast/schema.py
energy_assistant/api/forecast/use_cases.py
energy_assistant/api/forecast/views.py
energy_assistant/api/history/__init__.py
energy_assistant/api/history/schema.py
energy_assistant/api/history/use_cases.py
energy_assistant/api/history/views.py
energy_assistant/api/home_measurement/__init__.py
energy_assistant/api/home_measurement/schema.py
energy_assistant/api/home_measurement/use_cases.py
energy_assistant/api/home_measurement/views.py
energy_assistant/api/sessionlogs/__init__.py
energy_assistant/api/sessionlogs/schema.py
energy_assistant/api/sessionlogs/use_cases.py
energy_assistant/api/sessionlogs/views.py
energy_assistant/config/develop.env
energy_assistant/config/local.env
energy_assistant/config/test.env
energy_assistant/config/deviceregistry/v-zug/dishwasher adora s.yaml
energy_assistant/config/deviceregistry/v-zug/dryer adora TS WP.yaml
energy_assistant/devices/__init__.py
energy_assistant/devices/analysis.py
energy_assistant/devices/config.py
energy_assistant/devices/device.py
energy_assistant/devices/evcc.py
energy_assistant/devices/heat_pump.py
energy_assistant/devices/home.py
energy_assistant/devices/homeassistant.py
energy_assistant/devices/homeassistant_device.py
energy_assistant/devices/registry.py
energy_assistant-0.1.30.dist-info/METADATA
energy_assistant-0.1.30.dist-info/WHEEL
energy_assistant-0.1.30.dist-info/entry_points.txt
energy_assistant-0.1.30.dist-info/licenses/LICENSE
energy_assistant-0.1.30.dist-info/RECORD
