Metadata-Version: 2.4
Name: energy_assistant
Version: 0.1.30
Summary: Energy Assistant
Project-URL: Homepage, https://github.com/pail23/energy-assistant-backend
Author-email: The Energy Assistant Creators <pail23@users.noreply.github.com>
License: MIT License
License-File: LICENSE
Keywords: energy assistant,home assistant
Classifier: Programming Language :: Python
Classifier: Programming Language :: Python :: 3.12
Requires-Python: >=3.12
Requires-Dist: aiosqlite==0.21.0
Requires-Dist: alembic==1.16.4
Requires-Dist: apscheduler==3.11.0
Requires-Dist: colorlog==6.9.0
Requires-Dist: emhass==0.13.3
Requires-Dist: energy-assistant-frontend==0.0.70
Requires-Dist: fastapi[standard]==0.116.1
Requires-Dist: hass-client==1.2.0
Requires-Dist: jinja2==3.1.6
Requires-Dist: paho-mqtt==2.1.0
Requires-Dist: pydantic-settings==2.10.1
Requires-Dist: python-dotenv
Requires-Dist: pyyaml>=6.0.2
Requires-Dist: requests==2.32.5
Requires-Dist: sqlalchemy==2.0.43
